nonebot_plugin_setu/__init__.py
nonebot_plugin_setu/dao/__init__.py
nonebot_plugin_setu/dao/group_dao.py
nonebot_plugin_setu/dao/image_dao.py
nonebot_plugin_setu/dao/user_dao.py
nonebot_plugin_setu/file_tools.py
nonebot_plugin_setu/getPic.py
nonebot_plugin_setu/proxies.py
nonebot_plugin_setu/setu_api.py
nonebot_plugin_setu/utils.py
nonebot_plugin_setu/withdraw.py
nonebot_plugin_setu-1.1.11.dist-info/LICENSE
nonebot_plugin_setu-1.1.11.dist-info/METADATA
nonebot_plugin_setu-1.1.11.dist-info/WHEEL
nonebot_plugin_setu-1.1.11.dist-info/RECORD
