Metadata-Version: 2.1
Name: nonebot-plugin-setu
Version: 1.1.11
Summary: 基于lolicon api的涩图插件
Home-page: https://github.com/ayanamiblhx/nonebot_plugin_setu
License: Apache-2.0
Author: ayanamiblhx
Author-email: 1196818079@qq.com
Requires-Python: >=3.8,<4.0
Classifier: License :: OSI Approved :: Apache Software License
Classifier: Programming Language :: Python :: 3
Classifier: Programming Language :: Python :: 3.8
Classifier: Programming Language :: Python :: 3.9
Classifier: Programming Language :: Python :: 3.10
Classifier: Programming Language :: Python :: 3.11
Requires-Dist: httpx (>=0.23.0,<0.24.0)
Requires-Dist: httpx-socks (>=0.7.3,<0.8.0)
Requires-Dist: nonebot-adapter-onebot (>=2.0.0b1,<3.0.0)
Requires-Dist: nonebot2 (>=2.0.0b2,<3.0.0)
Requires-Dist: tqdm (>=4.61.0,<5.0.0)
Project-URL: Documentation, https://github.com/ayanamiblhx/nonebot_plugin_setu/blob/main/README.md
